animethemes_batch_encoder-2.4.dist-info/licenses/LICENSE
batch_encoder/__init__.py
batch_encoder/__main__.py
batch_encoder/_audio_filter.py
batch_encoder/_bitrate_mode.py
batch_encoder/_cli.py
batch_encoder/_colorspace.py
batch_encoder/_encode_webm.py
batch_encoder/_encoding_config.py
batch_encoder/_loudnorm_filter.py
batch_encoder/_seek.py
batch_encoder/_seek_collector.py
batch_encoder/_source_file.py
batch_encoder/_typing.py
batch_encoder/_utils.py
batch_encoder/_video_filter.py
animethemes_batch_encoder-2.4.dist-info/METADATA
animethemes_batch_encoder-2.4.dist-info/WHEEL
animethemes_batch_encoder-2.4.dist-info/top_level.txt
animethemes_batch_encoder-2.4.dist-info/RECORD
