Metadata-Version: 2.4
Name: animethemes-batch-encoder
Version: 2.4
Summary: Generate/Execute FFmpeg commands for files in acting directory
Home-page: https://github.com/AnimeThemes/animethemes-batch-encoder
Author: AnimeThemes
Author-email: admin@animethemes.moe
Classifier: Intended Audience :: Developers
Classifier: Programming Language :: Python :: 3.14
Classifier: Programming Language :: Python :: 3.15
Classifier: License :: OSI Approved :: MIT License
Classifier: Natural Language :: English
Classifier: Operating System :: OS Independent
Requires-Python: >=3.14
License-File: LICENSE
Requires-Dist: appdirs
Requires-Dist: inquirer
Dynamic: author
Dynamic: author-email
Dynamic: classifier
Dynamic: description
Dynamic: description-content-type
Dynamic: home-page
Dynamic: license-file
Dynamic: requires-dist
Dynamic: requires-python
Dynamic: summary
